odoo8_addon_sale_service_project-8.0.1.1.1.99.dev48-py3.8-nspkg.pth
odoo_addons/sale_service_project/README.rst
odoo_addons/sale_service_project/__init__.py
odoo_addons/sale_service_project/__openerp__.py
odoo_addons/sale_service_project/data/sale_service_project_demo.xml
odoo_addons/sale_service_project/i18n/am.po
odoo_addons/sale_service_project/i18n/ar.po
odoo_addons/sale_service_project/i18n/bg.po
odoo_addons/sale_service_project/i18n/bs.po
odoo_addons/sale_service_project/i18n/ca.po
odoo_addons/sale_service_project/i18n/ca_ES.po
odoo_addons/sale_service_project/i18n/cs.po
odoo_addons/sale_service_project/i18n/da.po
odoo_addons/sale_service_project/i18n/da_DK.po
odoo_addons/sale_service_project/i18n/de.po
odoo_addons/sale_service_project/i18n/el_GR.po
odoo_addons/sale_service_project/i18n/en_AU.po
odoo_addons/sale_service_project/i18n/en_GB.po
odoo_addons/sale_service_project/i18n/es.po
odoo_addons/sale_service_project/i18n/es_AR.po
odoo_addons/sale_service_project/i18n/es_CL.po
odoo_addons/sale_service_project/i18n/es_CO.po
odoo_addons/sale_service_project/i18n/es_CR.po
odoo_addons/sale_service_project/i18n/es_DO.po
odoo_addons/sale_service_project/i18n/es_EC.po
odoo_addons/sale_service_project/i18n/es_ES.po
odoo_addons/sale_service_project/i18n/es_MX.po
odoo_addons/sale_service_project/i18n/es_PE.po
odoo_addons/sale_service_project/i18n/es_PY.po
odoo_addons/sale_service_project/i18n/es_VE.po
odoo_addons/sale_service_project/i18n/et.po
odoo_addons/sale_service_project/i18n/fa.po
odoo_addons/sale_service_project/i18n/fi.po
odoo_addons/sale_service_project/i18n/fr.po
odoo_addons/sale_service_project/i18n/fr_CA.po
odoo_addons/sale_service_project/i18n/fr_CH.po
odoo_addons/sale_service_project/i18n/fr_FR.po
odoo_addons/sale_service_project/i18n/gl.po
odoo_addons/sale_service_project/i18n/gl_ES.po
odoo_addons/sale_service_project/i18n/he.po
odoo_addons/sale_service_project/i18n/hi.po
odoo_addons/sale_service_project/i18n/hr.po
odoo8_addon_sale_service_project-8.0.1.1.1.99.dev48.dist-info/METADATA
odoo8_addon_sale_service_project-8.0.1.1.1.99.dev48.dist-info/WHEEL
odoo8_addon_sale_service_project-8.0.1.1.1.99.dev48.dist-info/namespace_packages.txt
odoo8_addon_sale_service_project-8.0.1.1.1.99.dev48.dist-info/top_level.txt
odoo8_addon_sale_service_project-8.0.1.1.1.99.dev48.dist-info/RECORD
