Metadata-Version: 2.1
Name: odoo8-addon-sale-service-project
Version: 8.0.1.1.1.99.dev48
Summary: Sale Service Project
Home-page: http://www.tecnativa.com
Author: Tecnativa, Odoo Community Association (OCA)
Author-email: support@odoo-community.org
License: AGPL-3
Platform: UNKNOWN
Classifier: Programming Language :: Python
Classifier: Framework :: Odoo
Classifier: Framework :: Odoo :: 8.0
Classifier: License :: OSI Approved :: GNU Affero General Public License v3
Requires-Python: ~=2.7
Requires-Dist: odoo8-addon-project-task-materials
Requires-Dist: odoo (<9.0a,>=8.0a)
